fandomanime/__init__.py
fandomanime/getanime.py
fandomanime-0.0.3.dist-info/LICENSE
fandomanime-0.0.3.dist-info/METADATA
fandomanime-0.0.3.dist-info/WHEEL
fandomanime-0.0.3.dist-info/top_level.txt
fandomanime-0.0.3.dist-info/RECORD
