Metadata-Version: 2.1
Name: fandomanime
Version: 0.0.3
Summary: Simple web scraper for fandom anime summaries
Home-page: https://github.com/Matt711/animefandom
Author: Matthew Murray
Author-email: matthewmurray711@gmail.com
License: UNKNOWN
Platform: UNKNOWN
Classifier: Programming Language :: Python :: 3
Classifier: License :: OSI Approved :: MIT License
Classifier: Operating System :: OS Independent
Requires-Python: >=3.6
